hyperion/__init__.py
hyperion/py.typed
hyperion/api/__init__.py
hyperion/api/tune.py
hyperion/core/__init__.py
hyperion/core/bus.py
hyperion/core/capacity.py
hyperion/core/context.py
hyperion/core/controller.py
hyperion/core/effector.py
hyperion/core/events.py
hyperion/core/executor.py
hyperion/core/models.py
hyperion/core/state.py
hyperion/framework/__init__.py
hyperion/framework/experiment.py
hyperion/framework/policy.py
hyperion/framework/search_space.py
hyperion/framework/services.py
hyperion/policies/__init__.py
hyperion/policies/bayesian_optimization.py
hyperion/policies/beam_search.py
hyperion/policies/early_stopping.py
hyperion/policies/grid_search.py
hyperion/policies/llm_agent.py
hyperion/policies/llm_branching_agent.py
hyperion/policies/population_based_training.py
hyperion/policies/random_search.py
hyperion/storage/__init__.py
hyperion/storage/memory.py
hyperion/storage/sql.py
hyperion/visualization/__init__.py
hyperion/visualization/terminal.py
hyperion_opt-0.1.0.dist-info/licenses/LICENSE
hyperion_opt-0.1.0.dist-info/METADATA
hyperion_opt-0.1.0.dist-info/WHEEL
hyperion_opt-0.1.0.dist-info/top_level.txt
hyperion_opt-0.1.0.dist-info/RECORD
