Metadata-Version: 2.4
Name: hyperion-opt
Version: 0.1.0
Summary: Event-driven agentic hyperparameter optimization framework
Author: Joshua Yin
License: MIT
Project-URL: Homepage, https://github.com/Subjective/hyperion
Project-URL: Repository, https://github.com/Subjective/hyperion.git
Project-URL: Issues, https://github.com/Subjective/hyperion/issues
Project-URL: Documentation, https://github.com/Subjective/hyperion/tree/main/docs
Keywords: hyperparameter-optimization,machine-learning,automl,bayesian-optimization,grid-search,random-search,beam-search,population-based-training,event-driven,agentic
Classifier: Development Status :: 3 - Alpha
Classifier: Intended Audience :: Developers
Classifier: Intended Audience :: Science/Research
Classifier: License :: OSI Approved :: MIT License
Classifier: Operating System :: OS Independent
Classifier: Programming Language :: Python :: 3
Classifier: Programming Language :: Python :: 3.11
Classifier: Programming Language :: Python :: 3.12
Classifier: Programming Language :: Python :: 3.13
Classifier: Topic :: Scientific/Engineering :: Artificial Intelligence
Classifier: Topic :: Software Development :: Libraries :: Python Modules
Classifier: Typing :: Typed
Requires-Python: >=3.11
License-File: LICENSE
Requires-Dist: pydantic>=2.11.0
Requires-Dist: sqlalchemy>=2.0.0
Requires-Dist: aiosqlite>=0.21.0
Requires-Dist: aiofiles>=24.1.0
Requires-Dist: click>=8.2.0
Requires-Dist: pyyaml>=6.0.2
Requires-Dist: cloudpickle>=3.1.0
Requires-Dist: nest-asyncio>=1.6.0
Provides-Extra: dev
Requires-Dist: pytest>=8.4.0; extra == "dev"
Requires-Dist: pytest-asyncio>=1.1.0; extra == "dev"
Requires-Dist: pytest-cov>=6.2.0; extra == "dev"
Requires-Dist: ruff>=0.8.0; extra == "dev"
Requires-Dist: pyright>=1.1.400; extra == "dev"
Requires-Dist: pre-commit>=4.3.0; extra == "dev"
Requires-Dist: fastapi>=0.116.0; extra == "dev"
Requires-Dist: uvicorn>=0.35.0; extra == "dev"
Requires-Dist: websockets>=15.0.0; extra == "dev"
Requires-Dist: build>=1.3.0; extra == "dev"
Requires-Dist: twine>=6.2.0; extra == "dev"
Provides-Extra: viz
Requires-Dist: matplotlib>=3.10.6; extra == "viz"
Provides-Extra: ml
Requires-Dist: numpy>=2.3.2; extra == "ml"
Requires-Dist: scikit-learn>=1.7.1; extra == "ml"
Requires-Dist: scipy>=1.14.0; extra == "ml"
Requires-Dist: torch>=2.8.0; extra == "ml"
Requires-Dist: torchvision>=0.23.0; extra == "ml"
Dynamic: license-file
